xkcd_wrapper/__init__.py
xkcd_wrapper/async_client.py
xkcd_wrapper/base_client.py
xkcd_wrapper/client.py
xkcd_wrapper/comic.py
xkcd_wrapper/exceptions.py
xkcd_wrapper-1.0.2.dist-info/LICENSE
xkcd_wrapper-1.0.2.dist-info/METADATA
xkcd_wrapper-1.0.2.dist-info/WHEEL
xkcd_wrapper-1.0.2.dist-info/top_level.txt
xkcd_wrapper-1.0.2.dist-info/RECORD
