Metadata-Version: 2.1
Name: xkcd-wrapper
Version: 1.0.2
Summary: A wrapper for the xkcd API
Home-page: https://github.com/Kronopt/xkcd-wrapper
Author: Pedro HC David, https://github.com/Kronopt
License: GPLv3
Project-URL: Documentation, https://xkcd-wrapper.readthedocs.io/en/latest/
Keywords: xkcd wrapper xkcd-wrapper
Platform: UNKNOWN
Classifier: Development Status :: 5 - Production/Stable
Classifier: Intended Audience :: Developers
Classifier: License :: OSI Approved :: GNU General Public License v3 (GPLv3)
Classifier: Natural Language :: English
Classifier: Programming Language :: Python :: 3
Classifier: Programming Language :: Python :: 3.6
Classifier: Programming Language :: Python :: 3.7
Classifier: Programming Language :: Python :: 3.8
Classifier: Programming Language :: Python :: 3.9
Classifier: Programming Language :: Python :: 3.10
Provides-Extra: async
Requires-Dist: aiohttp (>=3.8.3,~=3.8.0) ; extra == 'async'
Provides-Extra: sync
Requires-Dist: requests (<2.29,>=2.27.0) ; extra == 'sync'
